setup.py
simplestats.egg-info/PKG-INFO
simplestats.egg-info/SOURCES.txt
simplestats.egg-info/dependency_links.txt
simplestats.egg-info/top_level.txt
src/__init__.py
src/__version__.py
src/aggregate.py
src/agreement.py
src/basic.py
src/comb.py
src/errors.py
src/freq.py
src/sequences.py
src/test_aggregate.py
src/test_agreement.py
src/test_basic.py
src/test_comb.py
src/test_freq.py
src/test_sequences.py