Metadata-Version: 1.0
Name: simplestats
Version: 0.2.0
Summary: Simple statistics modules for data analysis.
Home-page: http://bitbucket.org/lars512/simplestats/
Author: Lars Yencken
Author-email: lljy@csse.unimelb.edu.au
License: BSD
Platform: UNKNOWN
